ipa_scanner/__init__.py
ipa_scanner/excel_analyser.py
ipa_scanner/ipa_extractor.py
ipa_scanner/main.py
ipa_scanner-0.3.12.dist-info/licenses/LICENSE
ipa_scanner-0.3.12.dist-info/METADATA
ipa_scanner-0.3.12.dist-info/WHEEL
ipa_scanner-0.3.12.dist-info/entry_points.txt
ipa_scanner-0.3.12.dist-info/top_level.txt
ipa_scanner-0.3.12.dist-info/RECORD
